bublik/__init__.py
bublik/managers.py
bublik/model_mixin.py
bublik/tabl.py
django_bublik-0.1.4.dist-info/LICENSE
django_bublik-0.1.4.dist-info/METADATA
django_bublik-0.1.4.dist-info/WHEEL
django_bublik-0.1.4.dist-info/top_level.txt
django_bublik-0.1.4.dist-info/RECORD
